mfetch/__init__.py
mfetch/cimage.py
mfetch/get_info.py
mfetch/neofetch.py
mfetch/options
mfetch/colour/colours
mfetch/colour/colours.png
mfetch/logos/arch/dat
mfetch/logos/arch/logo-big.png
mfetch/logos/arch/logo.png
mfetch/logos/artix/dat
mfetch/logos/artix/logo-big.png
mfetch/logos/artix/logo.png
mfetch/logos/debian/dat
mfetch/logos/debian/logo-big.png
mfetch/logos/debian/logo.png
mfetch/logos/fedora/dat
mfetch/logos/fedora/logo-big.png
mfetch/logos/fedora/logo.png
mfetch/logos/gentoo/dat
mfetch/logos/gentoo/logo-big.png
mfetch/logos/gentoo/logo.png
mfetch/logos/haiku/dat
mfetch/logos/haiku/logo-big.png
mfetch/logos/haiku/logo.png
mfetch/logos/linux/dat
mfetch/logos/linux/logo-big.png
mfetch/logos/linux/logo.png
mfetch/logos/nixos/dat
mfetch/logos/nixos/logo-big.png
mfetch/logos/nixos/logo.png
mfetch/logos/opensuse/dat
mfetch/logos/opensuse/logo-big.png
mfetch/logos/opensuse/logo.png
mfetch/logos/pop!_os/dat
mfetch/logos/pop!_os/logo-big.png
mfetch/logos/pop!_os/logo.png
mfetch/logos/slackware/dat
mfetch/logos/slackware/logo-big.png
mfetch/logos/slackware/logo.png
mfetch/logos/ubuntu/dat
mfetch/logos/ubuntu/logo-big.png
mfetch/logos/ubuntu/logo.png
mfetch/logos/venom/logo-big.png
mfetch/logos/venom/logo.png
mfetch/logos/void/dat
mfetch/logos/void/logo-big.png
mfetch/logos/void/logo.png
mfetch/logos/windows/dat
mfetch/logos/windows/logo-big.png
mfetch/logos/windows/logo.png
mfetch/logos/xify/dat
mfetch/logos/xify/logo-big.png
mfetch/logos/xify/logo.png
mfetch-3.0.dist-info/licenses/LICENSE
mfetch-3.0.dist-info/METADATA
mfetch-3.0.dist-info/WHEEL
mfetch-3.0.dist-info/entry_points.txt
mfetch-3.0.dist-info/top_level.txt
mfetch-3.0.dist-info/RECORD
