Metadata-Version: 2.4
Name: mfetch
Version: 3.0
Summary: A terminal system information tool with customizable logos and colors.
Author: ['ToxicWaveHD', 'MannuVilasara']
License-File: LICENSE
Requires-Dist: Click
Requires-Dist: pillow
Dynamic: author
Dynamic: description
Dynamic: description-content-type
Dynamic: license-file
Dynamic: requires-dist
Dynamic: summary
